crypten/__init__.py
crypten/autograd_cryptensor.py
crypten/cryptensor.py
crypten/encoder.py
crypten/gradients.py
crypten/common/__init__.py
crypten/common/rng.py
crypten/common/tensor_types.py
crypten/common/util.py
crypten/communicator/__init__.py
crypten/communicator/communicator.py
crypten/communicator/distributed_communicator.py
crypten/communicator/in_process_communicator.py
crypten/debug/__init__.py
crypten/debug/debug.py
crypten/mpc/__init__.py
crypten/mpc/context.py
crypten/mpc/mpc.py
crypten/mpc/ptype.py
crypten/mpc/primitives/__init__.py
crypten/mpc/primitives/arithmetic.py
crypten/mpc/primitives/beaver.py
crypten/mpc/primitives/binary.py
crypten/mpc/primitives/circuit.py
crypten/mpc/primitives/converters.py
crypten/mpc/provider/__init__.py
crypten/mpc/provider/homomorphic_provider.py
crypten/mpc/provider/ttp_provider.py
crypten/nn/__init__.py
crypten/nn/loss.py
crypten/nn/module.py
crypten/nn/onnx_helper.py
crypten/nn/tensorboard.py
examples/__init__.py
examples/meters.py
examples/multiprocess_launcher.py
examples/util.py
test/__init__.py
test/benchmark_helper.py
test/benchmark_mpc.py
test/multiprocess_test_case.py
test/multithread_test_case.py
test/test_arithmetic.py
test/test_autograd.py
test/test_binary.py
test/test_common.py
test/test_communicator.py
test/test_context.py
test/test_crypten.py
test/test_debug.py
test/test_gradients.py
test/test_mpc.py
test/test_nn.py
test/test_tensorboard.py
th_seal-0.1.dist-info/LICENSE
th_seal-0.1.dist-info/METADATA
th_seal-0.1.dist-info/WHEEL
th_seal-0.1.dist-info/top_level.txt
th_seal-0.1.dist-info/RECORD
