Metadata-Version: 2.1
Name: th-seal
Version: 0.1
Summary: th-seal
Home-page: UNKNOWN
Author: OpenMined
Author-email: UNKNOWN
License: MIT License
Requires-Dist: onnx
Requires-Dist: tensorboard
Requires-Dist: future
